pion_ts/__init__.py
pion_ts/scanner.py
pion_ts-0.1.0.dist-info/LICENSE
pion_ts-0.1.0.dist-info/METADATA
pion_ts-0.1.0.dist-info/WHEEL
pion_ts-0.1.0.dist-info/top_level.txt
pion_ts-0.1.0.dist-info/RECORD
