Metadata-Version: 2.1
Name: pion-ts
Version: 0.1.0
Summary: Example extension for pion time series downloader.
Author-email: Emin Martinian <emin@aocks.com>
License: MIT License
License-File: LICENSE
Requires-Dist: requests
Requires-Dist: numpy
Requires-Dist: pandas
Requires-Dist: pion
Provides-Extra: dev
Requires-Dist: pytest; extra == "dev"
Requires-Dist: pylint; extra == "dev"
